uvicmuse_debug/Backend.py
uvicmuse_debug/__init__.py
uvicmuse_debug/__main__.py
uvicmuse_debug/constants.py
uvicmuse_debug/helper.py
uvicmuse_debug/interface.py
uvicmuse_debug/muse.py
uvicmuse_debug/docs/Header.png
uvicmuse_debug-1.0.1.dist-info/LICENSE.txt
uvicmuse_debug-1.0.1.dist-info/METADATA
uvicmuse_debug-1.0.1.dist-info/WHEEL
uvicmuse_debug-1.0.1.dist-info/entry_points.txt
uvicmuse_debug-1.0.1.dist-info/top_level.txt
uvicmuse_debug-1.0.1.dist-info/RECORD
