Metadata-Version: 2.1
Name: uvicmuse-debug
Version: 1.0.1
Summary: Stream and visualize EEG data from the Muse headset.
Home-page: UNKNOWN
Author: Bardia Barabadi
Author-email: bardiabarabadi@uvic.ca
License: MIT
Keywords: muse lsl eeg ble neuroscience matlab UDP
Platform: UNKNOWN
Classifier: Development Status :: 4 - Beta
Classifier: Intended Audience :: Science/Research
Classifier: Topic :: Software Development
Classifier: Operating System :: Microsoft :: Windows
Classifier: Operating System :: POSIX
Classifier: Operating System :: Unix
Classifier: Operating System :: MacOS
Classifier: Programming Language :: Python
Requires-Dist: bitstring
Requires-Dist: pygatt
Requires-Dist: pandas
Requires-Dist: scikit-learn
Requires-Dist: numpy
Requires-Dist: seaborn
Requires-Dist: pexpect
Requires-Dist: pillow
Requires-Dist: kivy
Requires-Dist: docutils
Requires-Dist: pygments
Requires-Dist: pyserial
Requires-Dist: esptool
Requires-Dist: pylsl ; platform_system != "Linux"
Requires-Dist: pylsl (==1.10.5) ; platform_system == "Linux"
Requires-Dist: pypiwin32 ; platform_system == "Windows"
Requires-Dist: kivy.deps.glew ; platform_system == "Windows"
Requires-Dist: kivy.deps.sdl2 ; platform_system == "Windows"
Requires-Dist: kivy.deps.gstreamer ; platform_system == "Windows"
